{
   "event":"pull_request_review",
   "id":"241f1090-1d8d-11e8-8364-9001e2c68b3d",
   "payload":{
      "action":"submitted",
      "review":{
         "id":100577362,
         "user":{
            "login":"rycao18stu",
            "id":21109009,
            "avatar_url":"https://avatars3.githubusercontent.com/u/21109009?v=4",
            "gravatar_id":"",
            "url":"https://api.github.com/users/rycao18stu",
            "html_url":"https://github.com/rycao18stu",
            "followers_url":"https://api.github.com/users/rycao18stu/followers",
            "following_url":"https://api.github.com/users/rycao18stu/following{/other_user}",
            "gists_url":"https://api.github.com/users/rycao18stu/gists{/gist_id}",
            "starred_url":"https://api.github.com/users/rycao18stu/starred{/owner}{/repo}",
            "subscriptions_url":"https://api.github.com/users/rycao18stu/subscriptions",
            "organizations_url":"https://api.github.com/users/rycao18stu/orgs",
            "repos_url":"https://api.github.com/users/rycao18stu/repos",
            "events_url":"https://api.github.com/users/rycao18stu/events{/privacy}",
            "received_events_url":"https://api.github.com/users/rycao18stu/received_events",
            "type":"User",
            "site_admin":false
         },
         "body":"",
         "commit_id":"84559e6d6bd2b99f8c2b62cb8b4b94985bd696bc",
         "submitted_at":"2018-03-01T20:14:26Z",
         "state":"approved",
         "html_url":"https://github.com/probotics2018/test/pull/90#pullrequestreview-100577362",
         "pull_request_url":"https://api.github.com/repos/probotics2018/test/pulls/90",
         "author_association":"NONE",
         "_links":{
            "html":{
               "href":"https://github.com/probotics2018/test/pull/90#pullrequestreview-100577362"
            },
            "pull_request":{
               "href":"https://api.github.com/repos/probotics2018/test/pulls/90"
            }
         }
      },
      "pull_request":{
         "url":"https://api.github.com/repos/probotics2018/test/pulls/90",
         "id":172341527,
         "html_url":"https://github.com/probotics2018/test/pull/90",
         "diff_url":"https://github.com/probotics2018/test/pull/90.diff",
         "patch_url":"https://github.com/probotics2018/test/pull/90.patch",
         "issue_url":"https://api.github.com/repos/probotics2018/test/issues/90",
         "number":90,
         "state":"open",
         "locked":false,
         "title":"push90",
         "user":{
            "login":"rycao18",
            "id":10412121,
            "avatar_url":"https://avatars0.githubusercontent.com/u/10412121?v=4",
            "gravatar_id":"",
            "url":"https://api.github.com/users/rycao18",
            "html_url":"https://github.com/rycao18",
            "followers_url":"https://api.github.com/users/rycao18/followers",
            "following_url":"https://api.github.com/users/rycao18/following{/other_user}",
            "gists_url":"https://api.github.com/users/rycao18/gists{/gist_id}",
            "starred_url":"https://api.github.com/users/rycao18/starred{/owner}{/repo}",
            "subscriptions_url":"https://api.github.com/users/rycao18/subscriptions",
            "organizations_url":"https://api.github.com/users/rycao18/orgs",
            "repos_url":"https://api.github.com/users/rycao18/repos",
            "events_url":"https://api.github.com/users/rycao18/events{/privacy}",
            "received_events_url":"https://api.github.com/users/rycao18/received_events",
            "type":"User",
            "site_admin":false
         },
         "body":"",
         "created_at":"2018-03-01T20:14:13Z",
         "updated_at":"2018-03-01T20:14:26Z",
         "closed_at":null,
         "merged_at":null,
         "merge_commit_sha":"8bc044917eaab3523e2dbfef616c04174c93452d",
         "assignee":null,
         "assignees":[

         ],
         "requested_reviewers":[
            {
               "login":"helenagao14",
               "id":21110270,
               "avatar_url":"https://avatars3.githubusercontent.com/u/21110270?v=4",
               "gravatar_id":"",
               "url":"https://api.github.com/users/helenagao14",
               "html_url":"https://github.com/helenagao14",
               "followers_url":"https://api.github.com/users/helenagao14/followers",
               "following_url":"https://api.github.com/users/helenagao14/following{/other_user}",
               "gists_url":"https://api.github.com/users/helenagao14/gists{/gist_id}",
               "starred_url":"https://api.github.com/users/helenagao14/starred{/owner}{/repo}",
               "subscriptions_url":"https://api.github.com/users/helenagao14/subscriptions",
               "organizations_url":"https://api.github.com/users/helenagao14/orgs",
               "repos_url":"https://api.github.com/users/helenagao14/repos",
               "events_url":"https://api.github.com/users/helenagao14/events{/privacy}",
               "received_events_url":"https://api.github.com/users/helenagao14/received_events",
               "type":"User",
               "site_admin":false
            }
         ],
         "requested_teams":[

         ],
         "labels":[

         ],
         "milestone":null,
         "commits_url":"https://api.github.com/repos/probotics2018/test/pulls/90/commits",
         "review_comments_url":"https://api.github.com/repos/probotics2018/test/pulls/90/comments",
         "review_comment_url":"https://api.github.com/repos/probotics2018/test/pulls/comments{/number}",
         "comments_url":"https://api.github.com/repos/probotics2018/test/issues/90/comments",
         "statuses_url":"https://api.github.com/repos/probotics2018/test/statuses/84559e6d6bd2b99f8c2b62cb8b4b94985bd696bc",
         "head":{
            "label":"probotics2018:Richard-branch",
            "ref":"Richard-branch",
            "sha":"84559e6d6bd2b99f8c2b62cb8b4b94985bd696bc",
            "user":{
               "login":"probotics2018",
               "id":35348102,
               "avatar_url":"https://avatars0.githubusercontent.com/u/35348102?v=4",
               "gravatar_id":"",
               "url":"https://api.github.com/users/probotics2018",
               "html_url":"https://github.com/probotics2018",
               "followers_url":"https://api.github.com/users/probotics2018/followers",
               "following_url":"https://api.github.com/users/probotics2018/following{/other_user}",
               "gists_url":"https://api.github.com/users/probotics2018/gists{/gist_id}",
               "starred_url":"https://api.github.com/users/probotics2018/starred{/owner}{/repo}",
               "subscriptions_url":"https://api.github.com/users/probotics2018/subscriptions",
               "organizations_url":"https://api.github.com/users/probotics2018/orgs",
               "repos_url":"https://api.github.com/users/probotics2018/repos",
               "events_url":"https://api.github.com/users/probotics2018/events{/privacy}",
               "received_events_url":"https://api.github.com/users/probotics2018/received_events",
               "type":"Organization",
               "site_admin":false
            },
            "repo":{
               "id":118814068,
               "name":"test",
               "full_name":"probotics2018/test",
               "owner":{
                  "login":"probotics2018",
                  "id":35348102,
                  "avatar_url":"https://avatars0.githubusercontent.com/u/35348102?v=4",
                  "gravatar_id":"",
                  "url":"https://api.github.com/users/probotics2018",
                  "html_url":"https://github.com/probotics2018",
                  "followers_url":"https://api.github.com/users/probotics2018/followers",
                  "following_url":"https://api.github.com/users/probotics2018/following{/other_user}",
                  "gists_url":"https://api.github.com/users/probotics2018/gists{/gist_id}",
                  "starred_url":"https://api.github.com/users/probotics2018/starred{/owner}{/repo}",
                  "subscriptions_url":"https://api.github.com/users/probotics2018/subscriptions",
                  "organizations_url":"https://api.github.com/users/probotics2018/orgs",
                  "repos_url":"https://api.github.com/users/probotics2018/repos",
                  "events_url":"https://api.github.com/users/probotics2018/events{/privacy}",
                  "received_events_url":"https://api.github.com/users/probotics2018/received_events",
                  "type":"Organization",
                  "site_admin":false
               },
               "private":false,
               "html_url":"https://github.com/probotics2018/test",
               "description":null,
               "fork":false,
               "url":"https://api.github.com/repos/probotics2018/test",
               "forks_url":"https://api.github.com/repos/probotics2018/test/forks",
               "keys_url":"https://api.github.com/repos/probotics2018/test/keys{/key_id}",
               "collaborators_url":"https://api.github.com/repos/probotics2018/test/collaborators{/collaborator}",
               "teams_url":"https://api.github.com/repos/probotics2018/test/teams",
               "hooks_url":"https://api.github.com/repos/probotics2018/test/hooks",
               "issue_events_url":"https://api.github.com/repos/probotics2018/test/issues/events{/number}",
               "events_url":"https://api.github.com/repos/probotics2018/test/events",
               "assignees_url":"https://api.github.com/repos/probotics2018/test/assignees{/user}",
               "branches_url":"https://api.github.com/repos/probotics2018/test/branches{/branch}",
               "tags_url":"https://api.github.com/repos/probotics2018/test/tags",
               "blobs_url":"https://api.github.com/repos/probotics2018/test/git/blobs{/sha}",
               "git_tags_url":"https://api.github.com/repos/probotics2018/test/git/tags{/sha}",
               "git_refs_url":"https://api.github.com/repos/probotics2018/test/git/refs{/sha}",
               "trees_url":"https://api.github.com/repos/probotics2018/test/git/trees{/sha}",
               "statuses_url":"https://api.github.com/repos/probotics2018/test/statuses/{sha}",
               "languages_url":"https://api.github.com/repos/probotics2018/test/languages",
               "stargazers_url":"https://api.github.com/repos/probotics2018/test/stargazers",
               "contributors_url":"https://api.github.com/repos/probotics2018/test/contributors",
               "subscribers_url":"https://api.github.com/repos/probotics2018/test/subscribers",
               "subscription_url":"https://api.github.com/repos/probotics2018/test/subscription",
               "commits_url":"https://api.github.com/repos/probotics2018/test/commits{/sha}",
               "git_commits_url":"https://api.github.com/repos/probotics2018/test/git/commits{/sha}",
               "comments_url":"https://api.github.com/repos/probotics2018/test/comments{/number}",
               "issue_comment_url":"https://api.github.com/repos/probotics2018/test/issues/comments{/number}",
               "contents_url":"https://api.github.com/repos/probotics2018/test/contents/{+path}",
               "compare_url":"https://api.github.com/repos/probotics2018/test/compare/{base}...{head}",
               "merges_url":"https://api.github.com/repos/probotics2018/test/merges",
               "archive_url":"https://api.github.com/repos/probotics2018/test/{archive_format}{/ref}",
               "downloads_url":"https://api.github.com/repos/probotics2018/test/downloads",
               "issues_url":"https://api.github.com/repos/probotics2018/test/issues{/number}",
               "pulls_url":"https://api.github.com/repos/probotics2018/test/pulls{/number}",
               "milestones_url":"https://api.github.com/repos/probotics2018/test/milestones{/number}",
               "notifications_url":"https://api.github.com/repos/probotics2018/test/notifications{?since,all,participating}",
               "labels_url":"https://api.github.com/repos/probotics2018/test/labels{/name}",
               "releases_url":"https://api.github.com/repos/probotics2018/test/releases{/id}",
               "deployments_url":"https://api.github.com/repos/probotics2018/test/deployments",
               "created_at":"2018-01-24T19:49:52Z",
               "updated_at":"2018-01-24T19:49:52Z",
               "pushed_at":"2018-03-01T20:14:13Z",
               "git_url":"git://github.com/probotics2018/test.git",
               "ssh_url":"git@github.com:probotics2018/test.git",
               "clone_url":"https://github.com/probotics2018/test.git",
               "svn_url":"https://github.com/probotics2018/test",
               "homepage":null,
               "size":2,
               "stargazers_count":0,
               "wat2018-03-01T20:14:27.441593+00:00 app[web.1]: chers_count":0,
               "language":null,
               "has_issues":true,
               "has_projects":true,
               "has_downloads":true,
               "has_wiki":true,
               "has_pages":false,
               "forks_count":0,
               "mirror_url":null,
               "archived":false,
               "open_issues_count":2,
               "license":null,
               "forks":0,
               "open_issues":2,
               "watchers":0,
               "default_branch":"master"
            }
         },
         "base":{
            "label":"probotics2018:master",
            "ref":"master",
            "sha":"9cf8977293a2c8d56744a9553f1012e901eaa7b1",
            "user":{
               "login":"probotics2018",
               "id":35348102,
               "avatar_url":"https://avatars0.githubusercontent.com/u/35348102?v=4",
               "gravatar_id":"",
               "url":"https://api.github.com/users/probotics2018",
               "html_url":"https://github.com/probotics2018",
               "followers_url":"https://api.github.com/users/probotics2018/followers",
               "following_url":"https://api.github.com/users/probotics2018/following{/other_user}",
               "gists_url":"https://api.github.com/users/probotics2018/gists{/gist_id}",
               "starred_url":"https://api.github.com/users/probotics2018/starred{/owner}{/repo}",
               "subscriptions_url":"https://api.github.com/users/probotics2018/subscriptions",
               "organizations_url":"https://api.github.com/users/probotics2018/orgs",
               "repos_url":"https://api.github.com/users/probotics2018/repos",
               "events_url":"https://api.github.com/users/probotics2018/events{/privacy}",
               "received_events_url":"https://api.github.com/users/probotics2018/received_events",
               "type":"Organization",
               "site_admin":false
            },
            "repo":{
               "id":118814068,
               "name":"test",
               "full_name":"probotics2018/test",
               "owner":{
                  "login":"probotics2018",
                  "id":35348102,
                  "avatar_url":"https://avatars0.githubusercontent.com/u/35348102?v=4",
                  "gravatar_id":"",
                  "url":"https://api.github.com/users/probotics2018",
                  "html_url":"https://github.com/probotics2018",
                  "followers_url":"https://api.github.com/users/probotics2018/followers",
                  "following_url":"https://api.github.com/users/probotics2018/following{/other_user}",
                  "gists_url":"https://api.github.com/users/probotics2018/gists{/gist_id}",
                  "starred_url":"https://api.github.com/users/probotics2018/starred{/owner}{/repo}",
                  "subscriptions_url":"https://api.github.com/users/probotics2018/subscriptions",
                  "organizations_url":"https://api.github.com/users/probotics2018/orgs",
                  "repos_url":"https://api.github.com/users/probotics2018/repos",
                  "events_url":"https://api.github.com/users/probotics2018/events{/privacy}",
                  "received_events_url":"https://api.github.com/users/probotics2018/received_events",
                  "type":"Organization",
                  "site_admin":false
               },
               "private":false,
               "html_url":"https://github.com/probotics2018/test",
               "description":null,
               "fork":false,
               "url":"https://api.github.com/repos/probotics2018/test",
               "forks_url":"https://api.github.com/repos/probotics2018/test/forks",
               "keys_url":"https://api.github.com/repos/probotics2018/test/keys{/key_id}",
               "collaborators_url":"https://api.github.com/repos/probotics2018/test/collaborators{/collaborator}",
               "teams_url":"https://api.github.com/repos/probotics2018/test/teams",
               "hooks_url":"https://api.github.com/repos/probotics2018/test/hooks",
               "issue_events_url":"https://api.github.com/repos/probotics2018/test/issues/events{/number}",
               "events_url":"https://api.github.com/repos/probotics2018/test/events",
               "assignees_url":"https://api.github.com/repos/probotics2018/test/assignees{/user}",
               "branches_url":"https://api.github.com/repos/probotics2018/test/branches{/branch}",
               "tags_url":"https://api.github.com/repos/probotics2018/test/tags",
               "blobs_url":"https://api.github.com/repos/probotics2018/test/git/blobs{/sha}",
               "git_tags_url":"https://api.github.com/repos/probotics2018/test/git/tags{/sha}",
               "git_refs_url":"https://api.github.com/repos/probotics2018/test/git/refs{/sha}",
               "trees_url":"https://api.github.com/repos/probotics2018/test/git/trees{/sha}",
               "statuses_url":"https://api.github.com/repos/probotics2018/test/statuses/{sha}",
               "languages_url":"https://api.github.com/repos/probotics2018/test/languages",
               "stargazers_url":"https://api.github.com/repos/probotics2018/test/stargazers",
               "contributors_url":"https://api.github.com/repos/probotics2018/test/contributors",
               "subscribers_url":"https://api.github.com/repos/probotics2018/test/subscribers",
               "subscription_url":"https://api.github.com/repos/probotics2018/test/subscription",
               "commits_url":"https://api.github.com/repos/probotics2018/test/commits{/sha}",
               "git_commits_url":"https://api.github.com/repos/probotics2018/test/git/commits{/sha}",
               "comments_url":"https://api.github.com/repos/probotics2018/test/comments{/number}",
               "issue_comment_url":"https://api.github.com/repos/probotics2018/test/issues/comments{/number}",
               "contents_url":"https://api.github.com/repos/probotics2018/test/contents/{+path}",
               "compare_url":"https://api.github.com/repos/probotics2018/test/compare/{base}...{head}",
               "merges_url":"https://api.github.com/repos/probotics2018/test/merges",
               "archive_url":"https://api.github.com/repos/probotics2018/test/{archive_format}{/ref}",
               "downloads_url":"https://api.github.com/repos/probotics2018/test/downloads",
               "issues_url":"https://api.github.com/repos/probotics2018/test/issues{/number}",
               "pulls_url":"https://api.github.com/repos/probotics2018/test/pulls{/number}",
               "milestones_url":"https://api.github.com/repos/probotics2018/test/milestones{/number}",
               "notifications_url":"https://api.github.com/repos/probotics2018/test/notifications{?since,all,participating}",
               "labels_url":"https://api.github.com/repos/probotics2018/test/labels{/name}",
               "releases_url":"https://api.github.com/repos/probotics2018/test/releases{/id}",
               "deployments_url":"https://api.github.com/repos/probotics2018/test/deployments",
               "created_at":"2018-01-24T19:49:52Z",
               "updated_at":"2018-01-24T19:49:52Z",
               "pushed_at":"2018-03-01T20:14:13Z",
               "git_url":"git://github.com/probotics2018/test.git",
               "ssh_url":"git@github.com:probotics2018/test.git",
               "clone_url":"https://github.com/probotics2018/test.git",
               "svn_url":"https://github.com/probotics2018/test",
               "homepage":null,
               "size":2,
               "stargazers_count":0,
               "watchers_count":0,
               "language":null,
               "has_issues":true,
               "has_projects":true,
               "has_downloads":true,
               "has_wiki":true,
               "has_pages":false,
               "forks_count":0,
               "mirror_url":null,
               "archived":false,
               "open_issues_count":2,
               "license":null,
               "forks":0,
               "open_issues":2,
               "watchers":0,
               "default_branch":"master"
            }
         },
         "_links":{
            "self":{
               "href":"https://api.github.com/repos/probotics2018/test/pulls/90"
            },
            "html":{
               "href":"https://github.com/probotics2018/test/pull/90"
            },
            "issue":{
               "href":"https://api.github.com/repos/probotics2018/test/issues/90"
            },
            "comments":{
               "href":"https://api.github.com/repos/probotics2018/test/issues/90/comments"
            },
            "review_comments":{
               "href":"https://api.github.com/repos/probotics2018/test/pulls/90/comments"
            },
            "review_comment":{
               "href":"https://api.github.com/repos/probotics2018/test/pulls/comments{/number}"
            },
            "commits":{
               "href":"https://api.github.com/repos/probotics2018/test/pulls/90/commits"
            },
            "statuses":{
               "href":"https://api.github.com/repos/probotics2018/test/statuses/84559e6d6bd2b99f8c2b62cb8b4b94985bd696bc"
            }
         },
         "author_association":"CONTRIBUTOR"
      },
      "repository":{
         "id":118814068,
         "name":"test",
         "full_name":"probotics2018/test",
         "owner":{
            "login":"probotics2018",
            "id":35348102,
            "avatar_url":"https://avatars0.githubusercontent.com/u/35348102?v=4",
            "gravatar_id":"",
            "url":"https://api.github.com/users/probotics2018",
            "html_url":"https://github.com/probotics2018",
            "followers_url":"https://api.github.com/users/probotics2018/followers",
            "following_url":"https://api.github.com/users/probotics2018/following{/other_user}",
            "gists_url":"https://api.github.com/users/probotics2018/gists{/gist_id}",
            "starred_url":"https://api.github.com/users/probotics2018/starred{/owner}{/repo}",
            "subscriptions_url":"https://api.github.com/users/probotics2018/subscriptions",
            "organizations_url":"https://api.github.com/users/probotics2018/orgs",
            "repos_url":"https://api.github.com/users/probotics2018/repos",
            "events_url":"https://api.github.com/users/probotics2018/events{/privacy}",
            "received_events_url":"https://api.github.com/users/probotics2018/received_events",
            "type":"Organization",
            "site_admin":false
         },
         "private":false,
         "html_url":"https://github.com/probotics2018/test",
         "description":null,
         "fork":false,
         "url":"https://api.github.com/repos/probotics2018/test",
         "forks_url":"https://api.github.com/repos/probotics2018/test/forks",
         "keys_url":"https://api.github.com/repos/probotics2018/test/keys{/key_id}",
         "collaborators_url":"https://api.github.com/repos/probotics2018/test/collaborators{/collaborator}",
         "teams_url":"https://api.github.com/repos/probotics2018/test/teams",
         "hooks_url":"https://api.github.com/repos/probotics2018/test/hooks",
         "issue_events_url":"https://api.github.com/repos/probotics2018/test/issues/events{/number}",
         "events_url":"https://api.github.com/repos/probotics2018/test/events",
         "assignees_url":"https://api.github.com/repos/probotics2018/test/assignees{/user}",
         "branches_url":"https://api.github.com/repos/probotics2018/test/branches{/branch}",
         "tags_url":"https://api.github.com/repos/probotics2018/test/tags",
         "blobs_url":"https://api.github.com/repos/probotics2018/test/git/blobs{/sha}",
         "git_tags_url":"https://api.github.com/repos/probotics2018/test/git/tags{/sha}",
         "git_refs_url":"https://api.github.com/repos/probotics2018/test/git/refs{/sha}",
         "trees_url":"https://api.github.com/repos/probotics2018/test/git/trees{/sha}",
         "statuses_url":"https://api.github.com/repos/probotics2018/test/statuses/{sha}",
         "languages_url":"https://api.github.com/repos/probotics2018/test/languages",
         "stargazers_url":"https://api.github.com/repos/probotics2018/test/stargazers",
         "contributors_url":"https://api.github.com/repos/probotics2018/test/contributors",
         "subscribers_url":"https://api.github.com/repos/probotics2018/test/subscribers",
         "subscription_url":"https://api.github.com/repos/probotics2018/test/subscription",
         "commits_url":"https://api.github.com/repos/probotics2018/test/commits{/sha}",
         "git_commits_url":"https://api.github.com/repos/probotics2018/test/git/commits{/sha}",
         "comments_url":"https://api.github.com/repos/probotics2018/test/comments{/number}",
         "issue_comment_url":"https://api.github.com/repos/probotics2018/test/issues/comments{/number}",
         "contents_url":"https://api.github.com/repos/probotics2018/test/contents/{+path}",
         "compare_url":"https2018-03-01T20:14:27.441593+00:00 app[web.1]: ://api.github.com/repos/probotics2018/test/compare/{base}...{head}",
         "merges_url":"https://api.github.com/repos/probotics2018/test/merges",
         "archive_url":"https://api.github.com/repos/probotics2018/test/{archive_format}{/ref}",
         "downloads_url":"https://api.github.com/repos/probotics2018/test/downloads",
         "issues_url":"https://api.github.com/repos/probotics2018/test/issues{/number}",
         "pulls_url":"https://api.github.com/repos/probotics2018/test/pulls{/number}",
         "milestones_url":"https://api.github.com/repos/probotics2018/test/milestones{/number}",
         "notifications_url":"https://api.github.com/repos/probotics2018/test/notifications{?since,all,participating}",
         "labels_url":"https://api.github.com/repos/probotics2018/test/labels{/name}",
         "releases_url":"https://api.github.com/repos/probotics2018/test/releases{/id}",
         "deployments_url":"https://api.github.com/repos/probotics2018/test/deployments",
         "created_at":"2018-01-24T19:49:52Z",
         "updated_at":"2018-01-24T19:49:52Z",
         "pushed_at":"2018-03-01T20:14:13Z",
         "git_url":"git://github.com/probotics2018/test.git",
         "ssh_url":"git@github.com:probotics2018/test.git",
         "clone_url":"https://github.com/probotics2018/test.git",
         "svn_url":"https://github.com/probotics2018/test",
         "homepage":null,
         "size":2,
         "stargazers_count":0,
         "watchers_count":0,
         "language":null,
         "has_issues":true,
         "has_projects":true,
         "has_downloads":true,
         "has_wiki":true,
         "has_pages":false,
         "forks_count":0,
         "mirror_url":null,
         "archived":false,
         "open_issues_count":2,
         "license":null,
         "forks":0,
         "open_issues":2,
         "watchers":0,
         "default_branch":"master"
      },
      "organization":{
         "login":"probotics2018",
         "id":35348102,
         "url":"https://api.github.com/orgs/probotics2018",
         "repos_url":"https://api.github.com/orgs/probotics2018/repos",
         "events_url":"https://api.github.com/orgs/probotics2018/events",
         "hooks_url":"https://api.github.com/orgs/probotics2018/hooks",
         "issues_url":"https://api.github.com/orgs/probotics2018/issues",
         "members_url":"https://api.github.com/orgs/probotics2018/members{/member}",
         "public_members_url":"https://api.github.com/orgs/probotics2018/public_members{/member}",
         "avatar_url":"https://avatars0.githubusercontent.com/u/35348102?v=4",
         "description":null
      },
      "sender":{
         "login":"rycao18stu",
         "id":21109009,
         "avatar_url":"https://avatars3.githubusercontent.com/u/21109009?v=4",
         "gravatar_id":"",
         "url":"https://api.github.com/users/rycao18stu",
         "html_url":"https://github.com/rycao18stu",
         "followers_url":"https://api.github.com/users/rycao18stu/followers",
         "following_url":"https://api.github.com/users/rycao18stu/following{/other_user}",
         "gists_url":"https://api.github.com/users/rycao18stu/gists{/gist_id}",
         "starred_url":"https://api.github.com/users/rycao18stu/starred{/owner}{/repo}",
         "subscriptions_url":"https://api.github.com/users/rycao18stu/subscriptions",
         "organizations_url":"https://api.github.com/users/rycao18stu/orgs",
         "repos_url":"https://api.github.com/users/rycao18stu/repos",
         "events_url":"https://api.github.com/users/rycao18stu/events{/privacy}",
         "received_events_url":"https://api.github.com/users/rycao18stu/received_events",
         "type":"User",
         "site_admin":false
      },
      "installation":{
         "id":82635
      }
   },
   "protocol":"http",
   "host":"hidden-caverns-26207.herokuapp.com",
   "url":"/",
   "github":{
      "config":{
         "debug":true,
         "host":"api.github.com",
         "pathPrefix":"/",
         "headers":{

         }
      },
      "debug":true,
      "acceptUrls":{
         "/orgs/:org/blocks":"application/vnd.github.giant-sentry-fist-preview+json",
         "/orgs/:org/blocks/:username":"application/vnd.github.giant-sentry-fist-preview+json",
         "/user/blocks":"application/vnd.github.giant-sentry-fist-preview+json",
         "/user/blocks/:username":"application/vnd.github.giant-sentry-fist-preview+json",
         "/codes_of_conduct":"application/vnd.github.scarlet-witch-preview+json",
         "/codes_of_conduct/:key":"application/vnd.github.scarlet-witch-preview+json",
         "/repos/:owner/:repo":"application/vnd.github.drax-preview+json",
         "/repos/:owner/:repo/community/code_of_conduct":"application/vnd.github.scarlet-witch-preview+json",
         "/search/commits":"application/vnd.github.cloak-preview+json",
         "/repos/:owner/:name/community/profile":"application/vnd.github.black-panther-preview+json",
         "/repos/:owner/:repo/deployments":"application/vnd.github.ant-man-preview+json",
         "/repos/:owner/:repo/deployments/:id/statuses":"application/vnd.github.ant-man-preview+json",
         "/users/:username/gpg_keys":"application/vnd.github.cryptographer-preview",
         "/user/gpg_keys":"application/vnd.github.cryptographer-preview",
         "/user/gpg_keys/:id":"application/vnd.github.cryptographer-preview",
         "/repos/:owner/:repo/commits/:sha":"application/vnd.github.cryptographer-preview",
         "/repos/:owner/:repo/import/authors":"application/vnd.github.barred-rock-preview",
         "/repos/:owner/:repo/import/authors/:author_id":"application/vnd.github.barred-rock-preview",
         "/:owner/:name/import/lfs":"application/vnd.github.barred-rock-preview",
         "/:owner/:name/import/large_files":"application/vnd.github.barred-rock-preview",
         "/repos/:owner/:repo/import":"application/vnd.github.barred-rock-preview",
         "/app/installations":"application/vnd.github.machine-man-preview",
         "/installations/:installation_id/access_tokens":"application/vnd.github.machine-man-preview",
         "/installation/repositories":"application/vnd.github.machine-man-preview",
         "/installations/:installation_id/repositories/:repository_id":"application/vnd.github.machine-man-preview",
         "/apps/:app_slug":"application/vnd.github.machine-man-preview",
         "/app/installations/:installation_id":"application/vnd.github.machine-man-preview",
         "/user/installations":"application/vnd.github.machine-man-preview",
         "/user/installations/:installation_id/repositories/:repository_id":"application/vnd.github.machine-man-preview",
         "/licenses":"application/vnd.github.drax-preview+json",
         "/licenses/:license":"application/vnd.github.drax-preview+json",
         "/repos/:owner/:repo/license":"application/vnd.github.drax-preview+json",
         "/marketplace_listing/plans":"application/vnd.github.valkyrie-preview+json",
         "/marketplace_listing/stubbed/plans":"application/vnd.github.valkyrie-preview+json",
         "/marketplace_listing/plans/:id/accounts":"application/vnd.github.valkyrie-preview+json",
         "/marketplace_listing/stubbed/plans/:id/accounts":"application/vnd.github.valkyrie-preview+json",
         "/marketplace_listing/accounts/:id":"application/vnd.github.valkyrie-preview+json",
         "/marketplace_listing/stubbed/accounts/:id":"application/vnd.github.valkyrie-preview+json",
         "/user/marketplace_purchases":"application/vnd.github.valkyrie-preview+json",
         "/user/marketplace_purchases/stubbed":"application/vnd.github.valkyrie-preview+json",
         "/orgs/:org/migrations":"application/vnd.github.wyandotte-preview+json",
         "/orgs/:org/migrations/:id":"application/vnd.github.wyandotte-preview+json",
         "/orgs/:org/migrations/:id/archive":"application/vnd.github.wyandotte-preview+json",
         "/orgs/:org/migrations/:id/repos/:repo_name/lock":"application/vnd.github.wyandotte-preview+json",
         "/orgs/:org/teams":"application/vnd.github.hellcat-preview+json",
         "/teams/:id":"application/vnd.github.hellcat-preview+json",
         "/teams/:id/teams":"application/vnd.github.hellcat-preview+json",
         "/teams/:id/members":"application/vnd.github.hellcat-preview+json",
         "/teams/:id/memberships/:username":"application/vnd.github.hellcat-preview+json",
         "/teams/:id/repos":"application/vnd.github.hellcat-preview+json",
         "/teams/:id/repos/:owner/:repo":"application/vnd.github.hellcat-preview+json",
         "/teams/:id/repos/:org/:repo":"application/vnd.github.hellcat-preview+json",
         "/user/teams":"application/vnd.github.hellcat-preview+json",
         "/repos/:owner/:repo/pages":"application/vnd.github.mister-fantastic-preview+json",
         "/repos/:owner/:repo/pages/builds":"application/vnd.github.mister-fantastic-preview+json",
         "/repos/:owner/:repo/pages/builds/latest":"application/vnd.github.mister-fantastic-preview+json",
         "/repos/:owner/:repo/pages/builds/:id":"application/vnd.github.mister-fantastic-preview+json",
         "/admin/pre-receive-environments/:id":"application/vnd.github.eye-scream-preview",
         "/admin/pre_receive_environments":"application/vnd.github.eye-scream-preview",
         "/admin/pre-receive-environments/:id/downloads/latest":"application/vnd.github.eye-scream-preview",
         "/admin/pre_receive_environments/:id/downloads":"application/vnd.github.eye-scream-preview",
         "/admin/pre-receive-hooks/:id":"application/vnd.github.eye-scream-preview",
         "/admin/pre-receive-hooks":"application/vnd.github.eye-scream-preview",
         "/repos/:owner/:repo/projects":"application/vnd.github.inertia-preview+json",
         "/orgs/:org/projects":"application/vnd.github.inertia-preview+json",
         "/projects/:id":"application/vnd.github.inertia-preview+json",
         "/projects/columns/:column_id/cards":"application/vnd.github.inertia-preview+json",
         "/projects/columns/cards/:id":"application/vnd.github.inertia-preview+json",
         "/projects/columns/cards/:id/moves":"application/vnd.github.inertia-preview+json",
         "/projects/:project_id/columns":"application/vnd.github.inertia-preview+json",
         "/projects/columns/:id":"application/vnd.github.inertia-preview+json",
         "/projects/columns/:id/moves":"application/vnd.github.inertia-preview+json",
         "/repos/:owner/:repo/pulls/:number/merge":"application/vnd.github.polaris-preview",
         "/issues":"application/vnd.github.squirrel-girl-preview",
         "/user/issues":"application/vnd.github.squirrel-girl-preview",
         "/orgs/:org/issues":"application/vnd.github.squirrel-girl-preview",
         "/repos/:owner/:repo/issues":"application/vnd.github.squirrel-girl-preview",
         "/repos/:owner/:repo/issues/:number":"application/vnd.github.squirrel-girl-preview",
         "/repos/:owner/:repo/comments/:id/reactions":"application/vnd.github.squirrel-girl-preview",
         "/repos/:owner/:repo/issues/comments":"application/vnd.github.squirrel-girl-preview",
         "/repos/:owner/:repo/issues/comments/:id":"application/vnd.github.squirrel-girl-preview",
         "/repos/:owner/:repo/issues/:number/comments":"application/vnd.github.squirrel-girl-preview",
         "/repos/:owner/:repo/issues/:number/reactions":"application/vnd.github.squirrel-girl-preview",
         "/repos/:owner/:repo/issues/comments/:id/reactions":"application/vnd.github.squirrel-girl-preview",
         "/repos/:owner/:repo/pulls/comments/:id/reactions":"application/vnd.github.squirrel-girl-2018-03-01T20:14:27.441593+00:00 app[web.1]: preview",
         "/reactions/:id":"application/vnd.github.squirrel-girl-preview",
         "/repos/:owner/:repo/pulls/:number/comments":"application/vnd.github.squirrel-girl-preview",
         "/repos/:owner/:repo/pulls/comments":"application/vnd.github.squirrel-girl-preview",
         "/repos/:owner/:repo/pulls/comments/:id":"application/vnd.github.squirrel-girl-preview",
         "/repos/:owner/:repo/pulls/:number/requested_reviewers":"application/vnd.github.thor-preview+json",
         "/repos/:owner/:repo/stargazers":"application/vnd.github.v3.star+json",
         "/users/:username/starred":"application/vnd.github.v3.star+json",
         "/user/starred":"application/vnd.github.v3.star+json",
         "/repos/:owner/:repo/issues/:issue_number/timeline":"application/vnd.github.mockingbird-preview",
         "/repos/:owner/:repo/topics":"application/vnd.github.mercy-preview+json",
         "/search/repositories":"application/vnd.github.mercy-preview+json"
      },
      "requestHeaders":[
         "authorization",
         "if-modified-since",
         "if-none-match",
         "cookie",
         "user-agent",
         "accept",
         "x-github-otp"
      ],
      "responseHeaders":[
         "x-ratelimit-limit",
         "x-ratelimit-remaining",
         "x-ratelimit-reset",
         "x-oauth-scopes",
         "x-poll-interval",
         "x-github-request-id",
         "x-github-media-type",
         "x-github-sso",
         "retry-after",
         "link",
         "location",
         "last-modified",
         "etag",
         "status"
      ],
      "authorization":{

      },
      "activity":{

      },
      "gists":{

      },
      "gitdata":{

      },
      "integrations":{

      },
      "apps":{

      },
      "issues":{

      },
      "migrations":{

      },
      "misc":{

      },
      "orgs":{

      },
      "projects":{

      },
      "pullRequests":{

      },
      "reactions":{

      },
      "repos":{

      },
      "search":{

      },
      "users":{

      },
      "enterprise":{

      },
      "limiter":{
         "maxNb":1,
         "minTime":1000,
         "highWater":-1,
         "strategy":1,
         "rejectOnDrop":false,
         "_nextRequest":1519935267438,
         "_nbRunning":0,
         "_queues":[
            {
               "_first":null,
               "_last":null,
               "length":0
            },
            {
               "_first":null,
               "_last":null,
               "length":0
            },
            {
               "_first":null,
               "_last":null,
               "length":0
            },
            {
               "_first":null,
               "_last":null,
               "length":0
            },
            {
               "_first":null,
               "_last":null,
               "length":0
            },
            {
               "_first":null,
               "_last":null,
               "length":0
            },
            {
               "_first":null,
               "_last":null,
               "length":0
            },
            {
               "_first":null,
               "_last":null,
               "length":0
            },
            {
               "_first":null,
               "_last":null,
               "length":0
            },
            {
               "_first":null,
               "_last":null,
               "length":0
            }
         ],
         "_running":{

         },
         "_nextIndex":0,
         "_unblockTime":0,
         "penalty":15000,
         "interrupt":false,
         "reservoir":null,
         "limiter":null,
         "events":{

         }
      },
      "auth":{
         "type":"token",
         "token":"v1.8052569b9185aa764768ab2bbdbd2ac3ef355078"
      }
   }
}